lambda_typing/__init__.py
lambda_typing/types.py
lambda_typing-0.1.0.dist-info/LICENSE
lambda_typing-0.1.0.dist-info/METADATA
lambda_typing-0.1.0.dist-info/WHEEL
lambda_typing-0.1.0.dist-info/top_level.txt
lambda_typing-0.1.0.dist-info/zip-safe
lambda_typing-0.1.0.dist-info/RECORD
