Metadata-Version: 1.2
Name: lambda-typing
Version: 0.1.0
Summary: Django JSON encoder with numpy support.
Home-page: https://github.com/illagrenan/lambda-typing
Author: Vasek Dohnal
Author-email: vaclav.dohnal@gmail.com
License: MIT
Project-URL: Source, https://github.com/illagrenan/lambda-typing
Project-URL: Tracker, https://github.com/illagrenan/lambda-typing/issues
Platform: UNKNOWN
Classifier: Development Status :: 4 - Beta
Classifier: Intended Audience :: Developers
Classifier: License :: OSI Approved :: MIT License
Classifier: Natural Language :: English
Classifier: Programming Language :: Python :: 3
Classifier: Programming Language :: Python :: 3 :: Only
Classifier: Programming Language :: Python :: 3.6
Classifier: Programming Language :: Python :: 3.7
Classifier: Operating System :: OS Independent
Classifier: Programming Language :: Python :: Implementation :: CPython
Classifier: Programming Language :: Python :: Implementation :: PyPy
Requires-Python: ~=3.6
